{
    "data": [
        {
            "type": "Cat",
            "items": [
                {
                    "id": 1,
                    "product": "สก็อตติช โฟลด์",
                    "pirce": "7,000",
                    "content": "หูพับ คือจุดขายของเขาเลย มีขนนุ่มนุ้บนิ้บ น่ากอด แต่เจ้าทาสอย่าแกงกันบ่อย เพราะพวกนางนิสัยอ่อนไหวง่าย ชอบแสดงอารมณ์ แต่ถ้าอารมณ์ดี ๆ ก็เล่นไม่หยุดเด้อ แถมแคล่วคล่อง ว่องไวไม่ใช่น้อย",
                    "img": "https://s359.kapook.com/pagebuilder/b0535efa-34f8-4c5f-9d56-4e5ff48878bc.jpg"
                },
                {
                    "id": 2,
                    "product": "เปอร์เซีย",
                    "pirce": "3,000",
                    "content": "โดดเด่นเรื่องรูปร่างสง่างาม ขนยาวฟูฟ่อง อ่อนนุ่ม นิสัยอ่อนโยนและคิวตี้มาก เข้ากับคนง่าย แถมเสียงร้องน่ารักน่าฟัง ตกเจ้าทาสได้สบาย ๆ",
                    "img": "https://s359.kapook.com/pagebuilder/c526e171-0e90-4539-a690-a079aeced8ea.jpg"
                },
                {
                    "id": 3,
                    "product": "บริติช ชอร์ตแฮร์",
                    "pirce": "40,000",
                    "content": "เป็นเหมียวรักสงบ เรียบร้อย ไม่เกรี้ยวกราด ไม่ชอบส่งเสียงรบกวนหรือทำลายข้าวของ เป็นมิตรกับเจ้าทาสทุกช่วงวัย มีอายุยืนมากกว่าแมวสายพันธุ์อื่น ๆ เล็กน้อย",
                    "img": "https://s359.kapook.com/pagebuilder/bfe266b0-2ba1-4fbc-b693-37f8a3759f66.jpg"
                },
                {
                    "id": 4,
                    "product": "เอ็กโซติก",
                    "pirce": "8,000",
                    "content": "เหมียวหน้าบูด จมูกหัก แต่ความน่ารักไม่เป็นสองรองใคร ซื่อสัตย์เป็นที่หนึ่ง แถมชิล ๆ ไม่ค่อยหงุดหงิด อดทนเก่ง รอเก่ง และที่สำคัญเงียบมากกก เจ้าทาสแทบจะไม่ได้ยินเสียงร้องของเจ้าเหมียวสายพันธุ์นี้เลย",
                    "img": "https://s359.kapook.com/pagebuilder/5974aa76-ec23-42aa-936d-e46d065a500e.jpg"
                },
                {
                    "id": 5,
                    "product": "เมนคูน",
                    "pirce": "10,000",
                    "content": "เป็นเหมียวยักษ์ ร่างกายใหญ่โต แต่นิสัยใจดี๊ใจดี จนได้รับสมญานามว่า Gentle Giant หากโตเต็มวัยจะมีความยาวตั้งแต่หัวจรดปลายหางประมาณ 1 เมตร มีนิสัยขี้อ้อน เล่นเก่ง ร่าเริงจนเจ้าทาสหลงหัวปักหัวปำ",
                    "img": "https://s359.kapook.com/pagebuilder/4fd01bb5-67e1-464e-8a8d-0beb3d18e38b.jpg"
                },
                {
                    "id": 1,
                    "product": "แมวป่านอร์เวย์",
                    "pirce": "20,700",
                    "content": "บรรพบุรุษของแมวสายพันธุ์นี้ ถูกผสมโดยชาวไวกิ้งมาตั้งแต่ 2,000 ปีที่แล้ว จุดเด่นของมันคือความงามของขนที่ยาวสลวย ที่มีไว้ป้องกันความหนาวเย็น นอกจากนั้นมันยังเป็นนักล่าที่ดีอีกด้วย",
                    "img": "https://petmaya.com/wp-content/uploads/2016/09/cat-price-01.jpg"
                },
                {
                    "id": 2,
                    "product": "แมวหิมาลายัน",
                    "pirce": "17,250 ",
                    "content": "แมวหิมาลายันค่อนข้างคล้ายคลึงกับแมวเปอร์เซีย แต่ลักษณะเด่นของมันคือมีตาสีฟ้า และมีสีลำตัวที่อ่อน แต่มีสีทึบที่บริเวณใบหน้า เท้า หู และหาง แมวสายพันธุ์นี้ถูกผสมขึ้นในช่วงปี 1950 ในอเมริกา มันมีนิสัยว่าง่าย อ่อนโยน เป็นมิตร และรักสงบ",
                    "img": "https://petmaya.com/wp-content/uploads/2016/09/cat-price-02.jpg"
                },
                {
                    "id": 3,
                    "product": "สกอตทิช โฟลด์",
                    "pirce": "6,900",
                    "content": "จุดเด่นที่สุดของสกอตทิชโฟลด์ คือใบหูที่พับลงมาน่ารักไม่เหมือนใคร ความแปลกนี้เป็นผลพวงมาจากการกลายพันธุ์ทางพันธุกรรม พวกมันเป็นแมวที่ฉลาด เข้ากับคนง่ายและพร้อมที่จะเล่นเสมอ นอกจากนั้น จุดเด่นของมันอีก 2 อย่างก็คือ มันชอบยืน 2 ขา และท่านั่งที่แปลกไม่เหมือนแมวสายพันธุ์ไหน",
                    "img": "https://petmaya.com/wp-content/uploads/2016/09/cat-price-03.jpg"
                },
                {
                    "id": 4,
                    "product": "ปีเตอร์บัลด์",
                    "pirce": "13,800",
                    "content": "ปีเตอร์บัลด์ หรือที่รู้จักกันในชื่อ ปีเตอร์สเบิร์ก สฟิงซ์ ถูกผสมในรัสเซียเมื่อปี 1994 จุดเด่นของพวกมันคือมีร่างกายที่ผอม หัวยาว และมีหูขนาดใหญ่ นอกจากนั้นพวกมันยังเป็นแมวที่เข้าสังคมได้ง่าย อ่อนโยน และฝึกง่าย",
                    "img": "https://petmaya.com/wp-content/uploads/2016/09/cat-price-04.jpg"
                },
                {
                    "id": 5,
                    "product": "อียิปเตียน โม",
                    "pirce": "17,250",
                    "content": "ลักษณะของแมวสายพันธุ์อียิปต์ชนิดนี้ เปลี่ยนไปเล็กน้อยในช่วง 3,000 ปีที่ผ่านมา ตั้งแต่สมัยอียิปต์โบราณ จุดเด่นของพวกมันคือมีจุดและลวดลายสีดำที่คล้ายกับเสือนั่นเอง",
                    "img": "https://petmaya.com/wp-content/uploads/2016/09/cat-price-05.jpg"
                }
            ]
        },
        {
            "type": "Dog",
            "items": [
                {
                    "id": 6,
                    "product": "อลาสกัน มาลามิวท์",
                    "pirce": "40,000",
                    "content": "อลาสกันจะตัวใหญ่กว่าชัดเจน แต่ในส่วนของความซุกซนนั่นก็แอบเป็นรองฮัสกี้อยู่นิดหน่อย จุดกำเนิดของสุนัขพันธุ์นี้มาจากชนเผ่ามาลามิวท์ (Malamute) ที่อาศัยอยู่ทางตอนเหนือของอลาสก้า ทำหน้าที่เป็นสุนัขลากเลื่อนของหนัก ๆ ไปตามเส้นทางหิมะ เพราะน้องหมาตัวใหญ่พันธุ์นี้มีพละกำลังมาก และแรงเยอะสุด ๆ ไปเลย",
                    "img": "https://static.wixstatic.com/media/ca4260_1bbc4802b9e84b3cb9257b27b47313a2~mv2.jpg/v1/fill/w_740,h_432,al_c,q_90/ca4260_1bbc4802b9e84b3cb9257b27b47313a2~mv2.webp"
                },
                {
                    "id": 7,
                    "product": "คอลลี่​",
                    "pirce": "6,000",
                    "content": "น้องหมาต้อนแกะแสนฉลาดของประเทศสกอตแลนด์ เป็นอีกหนึ่งหมาพันธุ์ใหญ่ขนยาวที่น่ารักตลอดกาล เพราะด้วยหน้าตาอันบ๊องแบ๊ว ผสานกับความฉลาดรอบรู้ของเจ้าตูบพันธุ์นี้ รับรองว่าจะต้องกลายเป็นที่รักของคนทั้งบ้านแน่นอน",
                    "img": "https://static.wixstatic.com/media/ca4260_0749524a2e6143899a93cff22ba9f4b3~mv2.jpg/v1/fill/w_740,h_555,al_c,q_90/ca4260_0749524a2e6143899a93cff22ba9f4b3~mv2.webp"
                },
                {
                    "id": 8,
                    "product": "ไซบีเรียน ฮัสกี้​",
                    "pirce": "6,000",
                    "content": "หนึ่งในสุนัขพันธุ์ใหญ่ที่นิยมเลี้ยงกันสุด ๆ ก็คงจะหนีไม่พ้นเจ้าฮัสกี้ ขนปุย ตาฟ้า มองมุมไหนก็หล่อเท่ห์ใช่เล่น สุนัขพันธุ์นี้ถือว่ามีพลังล้นเหลือ กระตือรือร้น มีเสน่ห์ในตัว มีความขี้อ้อน ชอบอยู่ใกล้เจ้าของ บางตัวมีพรสวรรค์สามารถพูดหรือร้องเพลงได้ด้วย",
                    "img": "https://static.wixstatic.com/media/ca4260_e17ed8414d5d44419e923e1f7e83cc53~mv2.jpg/v1/fill/w_740,h_493,al_c,q_90/ca4260_e17ed8414d5d44419e923e1f7e83cc53~mv2.webp"
                },
                {
                    "id": 7,
                    "product": "บีเกิ้ล​",
                    "pirce": "10,000",
                    "content": "สุนัขล่ากระต่ายในอดีต มีหูที่ยาวปรกลง มีทั้งพันธุ์ธรรมดา มีความสูงประมาณ 13-15 นิ้ว หนัก 18-20 ปอนด์ และพันธุ์อลิซาเบธ บีเกิ้ล (Elisabeth beagle) มีความสูงไม่เกิน 12 นิ้ว มีน้ำหนักไม่เกิน 20 ปอนด์ บี เกิ้ล มีถิ่นกำเนิดที่ประเทศอังกฤษ เป็นสุนัขรักสันติ รักเด็ก ไม่เพียงเป็นสุนัขล่าสัตว์อย่างกระต่ายในอดีต ในหลายร้อยปีก่อนบีเกิ้ลยังถูกนายพรานควบคุมเป็นฝูง",
                    "img": "https://www.dogthailand.net/data/attachment/forum/month_1502/15022711075bc175945312b51b.jpg"
                },
                {
                    "id": 8,
                    "product": "ยอร์กไชร์เทอร์เรีย",
                    "pirce": "8,000",
                    "content": "สุนัขตัวน้อย ขนยาว เส้นบาง มันวาวสลวย มีถิ่นกำเนิดในประเทศอังกฤษ ถือว่าเป็นสุนัขสวยงามมาก เป็นสัตว์เลี้ยงที่มีชีวิตชีวา รักเจ้าของ ขี้ประจบ สามารถปรับตัวให้เข้ากับชีวิตสังคมเล็กๆ เช่นในอพาร์ตเม้นต์ได้ดี ลักษณะทั่วไป สีมี 2 สีบนตัว สีน้ำตาลทองจะมีอยู่บนใบหน้า อก ท้อง และบริเวณปลายเท้า เส้นขนจะมีสีดำน้ำเงินที่โคนไล่ลงมาถึงตอนกลาง และจะมีสีน้ำตาลทองที่ส่วนปลายหัว ขนข้างจะมีขนาดเล็ก และเรียบไม่นูนกลม ปากแหลมยาวสมส่วน จมูกจะมีสีดำสนิท หูตั้งเป็นรูปตัววี มีขนสั้นๆ สีทองปกคลุม ขนยาวตรงปกคลุมทั้งตัว",
                    "img": "https://www.dogthailand.net/data/attachment/forum/month_1502/15022711071ab884c8d5ba78dd.jpg"
                }

            ]
        },
        {
            "type": "Rat",
            "items": [
                {
                    "id": 9,
                    "product": "ไจแอนท์",
                    "pirce": "300",
                    "content": "เป็นพันธ์ที่ตัวใหญ่ที่สุด มีทั้งขนยาว ขนสั้นมีสีและลวดลายเยอะ",
                    "img": "https://2.bp.blogspot.com/-d5NN6reC8sE/WxJlFVsmIJI/AAAAAAAAADo/pUstnNAf6aUw4J3wmi6HCnmtBderpuCEQCLcBGAs/s1600/67086650a.jpg"
                },
                {
                    "id": 10,
                    "product": "แคมเบล",
                    "pirce": "200",
                    "content": "จัดเป็นแฮมส์เตอร์แคระ ที่ตัวใหญ่ที่สุดในไทย แต่ไม่ใหญ่เท่า ไจแอนท์แต่พันธ์นี้ไม่นิยมเลี้ยง เพราะนิสัยที่เชื่องค่อนข้างยาก",
                    "img": "https://3.bp.blogspot.com/-94K5kfGy7Xo/WxJnGs2Er5I/AAAAAAAAAD0/HIkwQ7DJ_q4W_qxOuNB4qMmB6QJx-eEQQCLcBGAs/s320/IMG_5660.jpg"
                },
                {
                    "id": 9,
                    "product": "วินเทอร์ไวท์",
                    "pirce": "80",
                    "content": "ตัวเล็กรองลงมาจาก แคมเบลและเป็นพันธ์ที่นิยมเลี้ยงที่สุดในไทย",
                    "img": "https://pbs.twimg.com/media/EMHfyoHU4AALdvE.jpg"
                },
                {
                    "id": 10,
                    "product": "โรโบรอฟกี้",
                    "pirce": "100",
                    "content": "เป็นแฮมส์เตอร์แคระ ที่ตัวเล็กที่สุด ขี้ตกใจ วิ่งไว",
                    "img": "https://upload.wikimedia.org/wikipedia/commons/d/d3/Photo_of_Roborovski_Hamster.jpg"
                },
                {
                    "id": 10,
                    "product": "แกสบี้ อเมริกัน",
                    "pirce": "200",
                    "content": "สายพันธุ์แกสบี้อเมริกันนั้นจะมีขนสั้น เป็นหนึ่งในสายพันธุ์ที่มีความเก่าแก่ที่สุด ที่นักเพาะพันธุ์มีข้อมูล โดยมีต้นกำเนิดจากทางอเมริกาใต้",
                    "img": "https://3.bp.blogspot.com/-94K5kfGy7Xo/WxJnGs2Er5I/AAAAAAAAAD0/HIkwQ7DJ_q4W_qxOuNB4qMmB6QJx-eEQQCLcBGAs/s320/IMG_5660.jpg"
                },
                {
                    "id": 9,
                    "product": "แกสบี้ เร็กซ์",
                    "pirce": "80",
                    "content": "สายพันธุ์เร็กซ์มีขนสั้นชี้คล้ายรูปแบบของเม่น โดยจากข้อมูลบอกว่าเล็บของสายพันธ์ุเร็กซ์จะยาวเร็วเป็นพิเศษดังนั้นจึงต้องการการดูแลเพิ่มเล็กน้อย โดยควรจับมาดูบริเวณเล็บบ่อยๆว่ายาวหรือยัง",
                    "img": "https://pbs.twimg.com/media/EMHfyoHU4AALdvE.jpg"
                },
                {
                    "id": 10,
                    "product": "แกสบี้ เท็ดดี้",
                    "pirce": "1,500",
                    "content": "สายพันธุ์แกสบี้ เท็ดดี้นั้นจะมีลักษณะตัวสั้น โดยขนนั้นจะมีลักษณะคล้ายลวดโดยไม่ถึงขนาดหยิกมากนัก โดยสายพันธุ์เกิดขึ้นจากการกลายพันธุ์ด้านกรรมพันธุ์",
                    "img": "https://upload.wikimedia.org/wikipedia/commons/d/d3/Photo_of_Roborovski_Hamster.jpg"
                }
            ]
        }
    ]
}